loophopper/README.MD
loophopper/__init__.py
loophopper/requirements.txt
loophopper/thirdparty.json
loophopper-0.10.dist-info/LICENSE.rst
loophopper-0.10.dist-info/METADATA
loophopper-0.10.dist-info/WHEEL
loophopper-0.10.dist-info/top_level.txt
loophopper-0.10.dist-info/RECORD
