Metadata-Version: 2.1
Name: loophopper
Version: 0.10
Summary: A "fast-forward and rewind" custom iterator for flexible traversal through iterables
Home-page: https://github.com/hansalemaos/loophopper
Author: Johannes Fischer
Author-email: aulasparticularesdealemaosp@gmail.com
License: MIT
Keywords: fast-forward,rewind,loop
Classifier: Development Status :: 4 - Beta
Classifier: Programming Language :: Python :: 3 :: Only
Classifier: Programming Language :: Python :: 3.10
Classifier: Topic :: Software Development :: Libraries :: Python Modules
Classifier: Topic :: Utilities
License-File: LICENSE.rst
